{
  "id": 38134,
  "name": "Bioline Catgass Kit 12g",
  "slug": "bioline-cat-grass-kit-12g",
  "sku": "PSK-38134",
  "onSale": false,
  "price": null,
  "regularPrice": null,
  "salePrice": null,
  "currency": "KES",
  "currencySymbol": "KSh",
  "categories": [
    {
      "id": 2332,
      "name": "Cat Litter",
      "slug": "cat-litter"
    }
  ],
  "inStock": false,
  "averageRating": 0,
  "reviewCount": 0,
  "type": "simple",
  "description": "Grow delicious, organic and nutritious greens cats crave Easy-to-grow seeds sprout in days Kit includes cat grass seeds and soil in a recyclable container & small shovel Safe alternative to potentially poisonous houseplants and chemically treated lawns Dealing with hairballs disease (locally in the gut cat fur tufts) Improved plant fiber to help digestion and improve the resistance of the stomach Helps reduce bad breath, prevention of diseases of the mouth, gums, vitamin supplements and trace elements corresponding to inhibit and reduce gingivitis Ability to stimulate milk for the mother cat is pregnant and lactating.",
  "images": [],
  "tags": [],
  "brands": [],
  "stockStatus": "instock",
  "lowStockRemaining": null,
  "isPurchasable": true,
  "status": "publish",
  "featured": false,
  "catalogVisibility": "visible"
}