{
  "id": 50773,
  "name": "Maasai Shuka Blanket with Blue Fleece Lining- Medium",
  "slug": "maasai-shuka-blanket-with-blue-fleece-lining-medium-2",
  "sku": "MSMB@F",
  "onSale": true,
  "price": 1935,
  "regularPrice": 2150,
  "salePrice": 1935,
  "currency": "KES",
  "currencySymbol": "KSh",
  "thumbnail": "https://petstore.co.ke/wp-content/uploads/2024/08/20240731_165308-rotated.jpg",
  "categories": [
    {
      "id": 1204,
      "name": "Accessories",
      "slug": "accessories"
    },
    {
      "id": 2096,
      "name": "Generic",
      "slug": "generic"
    },
    {
      "id": 2243,
      "name": "Humans",
      "slug": "human"
    },
    {
      "id": 2261,
      "name": "Maasai Shukas",
      "slug": "maasai-shukas"
    }
  ],
  "brands": [
    {
      "id": 2449,
      "name": "Maasai Shukas",
      "slug": "maasai-shukas"
    }
  ],
  "tags": [],
  "inStock": false,
  "averageRating": 5,
  "reviewCount": 0,
  "type": "simple",
  "permalink": "https://petstore.co.ke/?post_type=product&p=50773",
  "shortDescription": "Experience the perfect fusion of cultural heritage and modern comfort with the Maasai Shuka Blanket with Blue Fleece Lining (Medium) . Designed with vibrant traditional Maasai patterns and paired with a luxuriously soft fleece interior, this blanket delivers warmth, style, and versatility for both personal and pet use. Whether used as a cozy lounging blanket, a decorative throw, or a comfortable resting surface for pets, it offers a unique blend of Kenyan artistry and everyday practicality. Measurements: 140cm x 90cm (L x W)",
  "description": "Key Features & Design Authentic Maasai Patterning: Showcases bold geometric designs and vibrant colors that honor the rich cultural heritage of the Maasai people. Soft Blue Fleece Lining: The plush, insulating interior provides exceptional warmth and comfort perfect for chilly evenings or for pets who love to snuggle. Versatile Functionality: Ideal as a pet bed blanket, sofa throw, decorative accent, or a cozy wrap for lounging at home. Durable & Easy to Maintain: Made from high-quality, long-lasting materials. The fleece is a washable machine, wrinkle-resistant, and designed for everyday use. Medium Size: Generously sized to support multiple uses, offering ample space for relaxation, warmth, and comfort. Benefits of the Fleece Lining Exceptional Insulation: Keeps users or pets warm throughout all seasons. Soft & Cozy Texture: Provides a soothing, comfortable surface for resting or sleeping. Breathable & Moisture-Wicking: Helps regulate body temperature and prevents overheating, ensuring all-day comfort. Lightweight & Portable: Easy to fold, carry, and transport—perfect for travel, outdoor activities, or picnics. Low Maintenance: Designed to stay fresh and clean with minimal effort, thanks to its durable, easy-care construction. &nbsp;",
  "images": [
    {
      "id": 49106,
      "src": "https://petstore.co.ke/wp-content/uploads/2024/08/20240731_165308-rotated.jpg",
      "alt": "Maasai Shuka Blanket with Blue Fleece Lining – Small",
      "name": "20240731_165308"
    },
    {
      "id": 49107,
      "src": "https://petstore.co.ke/wp-content/uploads/2024/08/20240731_165336.jpg",
      "alt": "Maasai Shuka Blanket with Blue Fleece Lining – Small",
      "name": "20240731_165336"
    }
  ],
  "stockStatus": "outofstock",
  "lowStockRemaining": null,
  "isPurchasable": true,
  "addToCartUrl": "https://petstore.co.ke/product/maasai-shuka-blanket-with-blue-fleece-lining-medium-2/?add-to-cart=50773",
  "status": "draft",
  "featured": false,
  "catalogVisibility": "visible",
  "dateCreated": "2024-10-13T12:36:48",
  "dateModified": "2026-06-17T04:34:01",
  "brand": "Maasai Shukas",
  "weight_kg": null,
  "animal_type": "dog",
  "food_type": "dry",
  "image_url": "https://petstore.co.ke/wp-content/uploads/2024/08/20240731_165308-rotated.jpg"
}