{
  "id": 70183,
  "name": "Proline Bentonite Clumping Cat Litter - Marseille Soap Scented 5L",
  "slug": "proline-bentonite-clumping-cat-litter-marseille-soap-scented-5l-3",
  "sku": "PCL007@OFFER",
  "onSale": true,
  "price": 882,
  "regularPrice": 1102,
  "salePrice": 882,
  "currency": "KES",
  "currencySymbol": "KSh",
  "thumbnail": "https://petstore.co.ke/wp-content/uploads/2023/03/Proline-Marseille-soap-5L.jpg",
  "categories": [
    {
      "id": 796,
      "name": "Proline",
      "slug": "proline"
    }
  ],
  "brands": [
    {
      "id": 2933,
      "name": "Proline",
      "slug": "proline"
    }
  ],
  "tags": [
    {
      "id": 831,
      "name": "bentonite",
      "slug": "bentonite"
    },
    {
      "id": 819,
      "name": "cat litter",
      "slug": "cat-litter"
    },
    {
      "id": 823,
      "name": "clumping",
      "slug": "clumping"
    },
    {
      "id": 939,
      "name": "On Sale Now",
      "slug": "sale"
    },
    {
      "id": 2315,
      "name": "scented",
      "slug": "scented"
    }
  ],
  "inStock": false,
  "averageRating": 5,
  "reviewCount": 0,
  "type": "simple",
  "permalink": "https://petstore.co.ke/?post_type=product&p=70183",
  "shortDescription": "Freshness made effortless. This Marseille Soap-scented bentonite cat litter absorbs quickly, prevents bacterial growth, and ensures a spotless litter box every time.",
  "description": "Proline Bentonite Clumping Marseille Soap Scented Cat Litter , 100% natural bentonite cat litter instantly clumps. Excellent pelletising, instantly lumps Neutralises odour with fresh Marseille Soap scent Non-toxic and 100% natural Thin grain shape Prevents bacterial growth Upon first use, we recommend adding new cat litter to the surface of the old cat litter for a few days.",
  "images": [
    {
      "id": 35909,
      "src": "https://petstore.co.ke/wp-content/uploads/2023/03/Proline-Marseille-soap-5L.jpg",
      "alt": "Proline Bentonite Clumping Cat Litter – Marseille Soap Scented 5L",
      "name": "Proline Marseille soap 5L"
    }
  ],
  "stockStatus": "outofstock",
  "lowStockRemaining": null,
  "isPurchasable": true,
  "addToCartUrl": "https://petstore.co.ke/product/proline-bentonite-clumping-cat-litter-marseille-soap-scented-5l-3/?add-to-cart=70183",
  "status": "draft",
  "featured": false,
  "catalogVisibility": "visible",
  "dateCreated": "2026-03-03T10:08:09",
  "dateModified": "2026-05-06T17:12:46",
  "brand": "Proline",
  "weight_kg": 4.8,
  "animal_type": "cat",
  "food_type": "dry",
  "image_url": "https://petstore.co.ke/wp-content/uploads/2023/03/Proline-Marseille-soap-5L.jpg"
}